odoo/addons/ir_config_parameter_multi_company/README.rst
odoo/addons/ir_config_parameter_multi_company/__init__.py
odoo/addons/ir_config_parameter_multi_company/__manifest__.py
odoo/addons/ir_config_parameter_multi_company/hooks.py
odoo/addons/ir_config_parameter_multi_company/i18n/es.po
odoo/addons/ir_config_parameter_multi_company/i18n/ir_config_parameter_multi_company.pot
odoo/addons/ir_config_parameter_multi_company/i18n/it.po
odoo/addons/ir_config_parameter_multi_company/models/__init__.py
odoo/addons/ir_config_parameter_multi_company/models/ir_config_parameter.py
odoo/addons/ir_config_parameter_multi_company/readme/CONTRIBUTORS.rst
odoo/addons/ir_config_parameter_multi_company/readme/DESCRIPTION.rst
odoo/addons/ir_config_parameter_multi_company/security/parameter_security.xml
odoo/addons/ir_config_parameter_multi_company/static/description/icon.png
odoo/addons/ir_config_parameter_multi_company/static/description/index.html
odoo/addons/ir_config_parameter_multi_company/tests/__init__.py
odoo/addons/ir_config_parameter_multi_company/tests/test_ir_config_parameter_multi_company.py
odoo/addons/ir_config_parameter_multi_company/views/ir_config_parameter_view.xml
odoo_addon_ir_config_parameter_multi_company-16.0.1.0.1.dist-info/METADATA
odoo_addon_ir_config_parameter_multi_company-16.0.1.0.1.dist-info/WHEEL
odoo_addon_ir_config_parameter_multi_company-16.0.1.0.1.dist-info/top_level.txt
odoo_addon_ir_config_parameter_multi_company-16.0.1.0.1.dist-info/RECORD
